dora_qwenvl/__init__.py
dora_qwenvl/main.py
dora_qwenvl-0.3.13.dist-info/METADATA
dora_qwenvl-0.3.13.dist-info/WHEEL
dora_qwenvl-0.3.13.dist-info/entry_points.txt
dora_qwenvl-0.3.13.dist-info/top_level.txt
dora_qwenvl-0.3.13.dist-info/RECORD
