Metadata-Version: 2.4
Name: dora-qwenvl
Version: 0.3.13
Summary: Dora Node for VLM
Author-email: Haixuan Xavier Tao <tao.xavier@outlook.com>, Enzo Le Van <dev@enzo-le-van.fr>
License: MIT
Requires-Python: >=3.9
Requires-Dist: dora-rs>=0.3.9
Requires-Dist: numpy<2.0.0
Requires-Dist: torch>=2.7.0
Requires-Dist: torchvision>=0.22
Requires-Dist: torchaudio>=2.7.0
Requires-Dist: qwen-vl-utils>=0.0.5
Requires-Dist: opencv-python>=4.1.1
Requires-Dist: modelscope>=1.18.1
Requires-Dist: peft==0.13.2
Requires-Dist: accelerate>=1.3.0
Requires-Dist: transformers
